[
    {
        "model": "auth.Group",
        "pk": 1,
        "fields": {
            "name": "anyuser"
        }
    },
    {
        "model": "auth.Group",
        "pk": 2,
        "fields": {
            "name": "authuser"
        }
    },


    {
        "model": "geocamUsers.Folder",
        "pk": 1,
        "fields": {
            "name": "root",
            "parent": null
        }
    },


    {
        "model": "geocamUsers.GroupPermission",
        "pk": null,
        "fields": {
            "folder": 1,
            "canView": true,
            "canList": true,
            "group": 1
        }
    }
]
